plusdeck/__init__.py
plusdeck/__main__.py
plusdeck/cli.py
plusdeck/client.py
plusdeck/config.py
plusdeck/jupyter.py
plusdeck/py.typed
plusdeck/test.py
plusdeck/dbus/__init__.py
plusdeck/dbus/config.py
plusdeck/dbus/domain.py
plusdeck/dbus/error.py
plusdeck/dbus/interface.py
plusdeck/dbus/select.py
plusdeck/dbus/client/__init__.py
plusdeck/dbus/client/__main__.py
plusdeck/dbus/client/cli.py
plusdeck/dbus/service/__init__.py
plusdeck/dbus/service/__main__.py
plusdeck/dbus/service/cli.py
plusdeck-5.0.1.dist-info/licenses/LICENSE
plusdeck-5.0.1.dist-info/METADATA
plusdeck-5.0.1.dist-info/WHEEL
plusdeck-5.0.1.dist-info/top_level.txt
plusdeck-5.0.1.dist-info/RECORD
