Metadata-Version: 2.4
Name: plusdeck
Version: 5.0.1
Summary: Serial client and Linux service for Plus Deck 2C PC Cassette Deck
Author-email: Josh Holbrook <josh.holbrook@gmail.com>
License: MPL-2.0
Classifier: Programming Language :: Python
Classifier: Development Status :: 4 - Beta
Classifier: Intended Audience :: Developers
Classifier: License :: OSI Approved :: Mozilla Public License 2.0 (MPL 2.0)
Classifier: Operating System :: OS Independent
Classifier: Operating System :: POSIX :: Linux
Classifier: Programming Language :: Python
Classifier: Programming Language :: Python :: 3
Classifier: Programming Language :: Python :: 3.11
Classifier: Programming Language :: Python :: 3.12
Classifier: Programming Language :: Python :: 3.13
Classifier: Topic :: System :: Hardware
Classifier: Topic :: System :: Hardware :: Hardware Drivers
Classifier: Topic :: Terminals :: Serial
Requires-Python: >=3.11
License-File: LICENSE
Requires-Dist: click
Requires-Dist: configurence
Requires-Dist: ipywidgets
Requires-Dist: pyee
Requires-Dist: pyserial
Requires-Dist: pyserial-asyncio
Requires-Dist: pyyaml
Provides-Extra: dbus
Requires-Dist: sdbus; extra == "dbus"
Dynamic: license-file
